leakcleaner/__init__.py
leakcleaner/cli.py
leakcleaner/leakcleaner.py
leakcleaner-0.1.0.dist-info/AUTHORS.rst
leakcleaner-0.1.0.dist-info/LICENSE
leakcleaner-0.1.0.dist-info/METADATA
leakcleaner-0.1.0.dist-info/WHEEL
leakcleaner-0.1.0.dist-info/entry_points.txt
leakcleaner-0.1.0.dist-info/top_level.txt
leakcleaner-0.1.0.dist-info/RECORD
