Metadata-Version: 2.1
Name: leakcleaner
Version: 0.1.0
Summary: Functionalities and cli tool to fetch, parse and normalize raw dataleak data.
Home-page: https://github.com/weallfloatdownhere/leakcleaner
Author: NoHandle
Author-email: nohandler@admin.com
License: MIT license
Keywords: leakcleaner
Platform: UNKNOWN
Classifier: Development Status :: 2 - Pre-Alpha
Classifier: Intended Audience :: Developers
Classifier: License :: OSI Approved :: MIT License
Classifier: Natural Language :: English
Classifier: Programming Language :: Python :: 3
Classifier: Programming Language :: Python :: 3.6
Classifier: Programming Language :: Python :: 3.7
Classifier: Programming Language :: Python :: 3.8
Requires-Python: >=3.6
License-File: LICENSE
License-File: AUTHORS.rst
Requires-Dist: Click (>=7.0)
Requires-Dist: pydantic (==1.10.2)
